battlehack20/__init__.py
battlehack20/stubs.py
battlehack20/engine/__init__.py
battlehack20/engine/container/__init__.py
battlehack20/engine/container/code_container.py
battlehack20/engine/container/instruction.py
battlehack20/engine/container/instrument.py
battlehack20/engine/container/runner.py
battlehack20/engine/game/__init__.py
battlehack20/engine/game/constants.py
battlehack20/engine/game/game.py
battlehack20/engine/game/robot.py
battlehack20/engine/game/robottype.py
battlehack20/engine/game/team.py
battlehack20/engine/game/viewer.py
battlehack20-1.1.0.dist-info/METADATA
battlehack20-1.1.0.dist-info/WHEEL
battlehack20-1.1.0.dist-info/top_level.txt
battlehack20-1.1.0.dist-info/RECORD
